{
    "name": "Character Roomba",
    "quadData": [
        {
            "type": "quad",
            "texture": "texCharRoomba",
            "frame": 0,
            "position": {
                "x": 0,
                "y": 0,
                "z": 0
            },
            "points": [
                {
                    "x": 10,
                    "y": -12,
                    "z": 0
                },
                {
                    "x": -10,
                    "y": -12,
                    "z": 0
                },
                {
                    "x": -10,
                    "y": 0,
                    "z": 0
                },
                {
                    "x": 10,
                    "y": 0,
                    "z": 0
                }
            ]
        }
    ],
    "collisionData": [
        {
            "type": "collisionQuad",
            "position": {
                "x": 0,
                "y": 0,
                "z": 0
            },
            "points": [
                {
                    "x": -6,
                    "y": 0,
                    "z": 0
                },
                {
                    "x": 6,
                    "y": 0,
                    "z": 0
                },
                {
                    "x": 6,
                    "y": -12,
                    "z": 0
                },
                {
                    "x": -6,
                    "y": -12,
                    "z": 0
                }
            ]
        }
    ]
}