{"name":"Hangar Hallway","quadData":[{"type":"quad","texture":"texMetalHangarLineEnd","frame":0,"position":{"x":0,"y":0,"z":0},"points":[{"x":0,"y":0,"z":16},{"x":0,"y":0,"z":-16},{"x":32,"y":0,"z":-16},{"x":32,"y":0,"z":16}]},{"type":"quad","texture":"texMetalHangarLineCurve","frame":0,"position":{"x":0,"y":0,"z":0},"points":[{"x":-32,"y":0,"z":16},{"x":-32,"y":0,"z":-16},{"x":0,"y":0,"z":-16},{"x":0,"y":0,"z":16}]},{"type":"quad","texture":"texMetalHangar00","frame":0,"position":{"x":0,"y":0,"z":0},"points":[{"x":0,"y":0,"z":16},{"x":32,"y":0,"z":16},{"x":32,"y":0,"z":48},{"x":0,"y":0,"z":48}]},{"type":"quad","texture":"texMetalHangarLineT","frame":0,"position":{"x":0,"y":0,"z":0},"points":[{"x":0,"y":0,"z":16},{"x":0,"y":0,"z":48},{"x":-32,"y":0,"z":48},{"x":-32,"y":0,"z":16}]},{"type":"quad","texture":"texMetalHangarLineStraight","frame":0,"position":{"x":0,"y":0,"z":0},"points":[{"x":-32,"y":0,"z":48},{"x":0,"y":0,"z":48},{"x":0,"y":0,"z":80},{"x":-32,"y":0,"z":80}]},{"type":"quad","texture":"texMetalHangar01","frame":0,"position":{"x":0,"y":0,"z":0},"points":[{"x":0,"y":0,"z":48},{"x":32,"y":0,"z":48},{"x":32,"y":0,"z":80},{"x":0,"y":0,"z":80}]},{"type":"quad","texture":"texMetalHangar00","frame":0,"position":{"x":0,"y":0,"z":0},"points":[{"x":0,"y":0,"z":80},{"x":32,"y":0,"z":80},{"x":32,"y":0,"z":112},{"x":0,"y":0,"z":112}]},{"type":"quad","texture":"texMetalHangarLineStraight","frame":0,"position":{"x":0,"y":0,"z":0},"points":[{"x":-32,"y":0,"z":80},{"x":0,"y":0,"z":80},{"x":0,"y":0,"z":112},{"x":-32,"y":0,"z":112}]},{"type":"quad","texture":"texMetalHangarLineCurve","frame":0,"position":{"x":0,"y":0,"z":0},"points":[{"x":0,"y":0,"z":144},{"x":-32,"y":0,"z":144},{"x":-32,"y":0,"z":112},{"x":0,"y":0,"z":112}]},{"type":"quad","texture":"texMetalHangarLineCurve","frame":0,"position":{"x":0,"y":0,"z":0},"points":[{"x":0,"y":0,"z":112},{"x":32,"y":0,"z":112},{"x":32,"y":0,"z":144},{"x":0,"y":0,"z":144}]},{"type":"quad","texture":"texMetalHangarLineStraight","frame":0,"position":{"x":0,"y":0,"z":0},"points":[{"x":0,"y":0,"z":144},{"x":32,"y":0,"z":144},{"x":32,"y":0,"z":176},{"x":0,"y":0,"z":176}]},{"type":"quad","texture":"texMetalHangar02","frame":0,"position":{"x":0,"y":0,"z":0},"points":[{"x":-32,"y":0,"z":144},{"x":0,"y":0,"z":144},{"x":0,"y":0,"z":176},{"x":-32,"y":0,"z":176}]},{"type":"quad","texture":"texMetalHangar01","frame":0,"position":{"x":0,"y":0,"z":0},"points":[{"x":-32,"y":0,"z":176},{"x":0,"y":0,"z":176},{"x":0,"y":0,"z":208},{"x":-32,"y":0,"z":208}]},{"type":"quad","texture":"texMetalHangarLineStraight","frame":0,"position":{"x":0,"y":0,"z":0},"points":[{"x":0,"y":0,"z":176},{"x":32,"y":0,"z":176},{"x":32,"y":0,"z":208},{"x":0,"y":0,"z":208}]},{"type":"quad","texture":"texMetalHangar02","frame":0,"position":{"x":0,"y":0,"z":0},"points":[{"x":-64,"y":4,"z":-16},{"x":-32,"y":0,"z":-16},{"x":-32,"y":0,"z":16},{"x":-60,"y":4,"z":16}]},{"type":"quad","texture":"texMetalHangarLineStraight","frame":0,"position":{"x":0,"y":0,"z":0},"points":[{"x":-56,"y":4,"z":48},{"x":-60,"y":4,"z":16},{"x":-32,"y":0,"z":16},{"x":-32,"y":0,"z":48}]},{"type":"quad","texture":"texMetalHangar01","frame":0,"position":{"x":0,"y":0,"z":0},"points":[{"x":-100,"y":8,"z":-4},{"x":-64,"y":4,"z":-16},{"x":-60,"y":4,"z":16},{"x":-92,"y":8,"z":24}]},{"type":"quad","texture":"texMetalHangarLineStraight","frame":0,"position":{"x":0,"y":0,"z":0},"points":[{"x":-60,"y":4,"z":16},{"x":-56,"y":4,"z":48},{"x":-76,"y":8,"z":52},{"x":-92,"y":8,"z":24}]},{"type":"quad","texture":"texMetalHangar02","frame":0,"position":{"x":0,"y":0,"z":0},"points":[{"x":-132,"y":12,"z":16},{"x":-100,"y":8,"z":-4},{"x":-92,"y":8,"z":24},{"x":-116,"y":12,"z":40}]},{"type":"quad","texture":"texMetalHangarLineStraight","frame":0,"position":{"x":0,"y":0,"z":0},"points":[{"x":-96,"y":12,"z":64},{"x":-116,"y":12,"z":40},{"x":-92,"y":8,"z":24},{"x":-76,"y":8,"z":52}]},{"type":"quad","texture":"texMetalHangarLineStraight","frame":0,"position":{"x":0,"y":0,"z":0},"points":[{"x":-108,"y":16,"z":76},{"x":-132,"y":16,"z":60},{"x":-116,"y":12,"z":40},{"x":-96,"y":12,"z":64}]},{"type":"quad","texture":"texMetalHangarLineStraight","frame":0,"position":{"x":0,"y":0,"z":0},"points":[{"x":-116,"y":20,"z":96},{"x":-144,"y":20,"z":88},{"x":-132,"y":16,"z":60},{"x":-108,"y":16,"z":76}]},{"type":"quad","texture":"texMetalHangar00","frame":0,"position":{"x":0,"y":0,"z":0},"points":[{"x":-176,"y":20,"z":80},{"x":-160,"y":16,"z":44},{"x":-132,"y":16,"z":60},{"x":-144,"y":20,"z":88}]},{"type":"quad","texture":"texMetalHangarLineCurve","frame":0,"position":{"x":0,"y":0,"z":0},"points":[{"x":-116,"y":20,"z":96},{"x":-120,"y":24,"z":120},{"x":-152,"y":24,"z":116},{"x":-144,"y":20,"z":88}]},{"type":"quad","texture":"texMetalHangarLineCurve","frame":0,"position":{"x":0,"y":0,"z":0},"points":[{"x":-184,"y":24,"z":112},{"x":-176,"y":20,"z":80},{"x":-144,"y":20,"z":88},{"x":-152,"y":24,"z":116}]},{"type":"quad","texture":"texMetalHangar02","frame":0,"position":{"x":0,"y":0,"z":0},"points":[{"x":-152,"y":24,"z":116},{"x":-120,"y":24,"z":120},{"x":-120,"y":28,"z":144},{"x":-152,"y":28,"z":144}]},{"type":"quad","texture":"texMetalHangarLineStraight","frame":0,"position":{"x":0,"y":0,"z":0},"points":[{"x":-184,"y":24,"z":112},{"x":-152,"y":24,"z":116},{"x":-152,"y":28,"z":144},{"x":-184,"y":28,"z":144}]},{"type":"quad","texture":"texMetalHangarLineStraight","frame":0,"position":{"x":0,"y":0,"z":0},"points":[{"x":-184,"y":28,"z":144},{"x":-152,"y":28,"z":144},{"x":-152,"y":32,"z":172},{"x":-184,"y":32,"z":176}]},{"type":"quad","texture":"texMetalHangar00","frame":0,"position":{"x":0,"y":0,"z":0},"points":[{"x":-152,"y":28,"z":144},{"x":-120,"y":28,"z":144},{"x":-120,"y":32,"z":168},{"x":-152,"y":32,"z":172}]},{"type":"quad","texture":"texMetalHangarLineStraight","frame":0,"position":{"x":0,"y":0,"z":0},"points":[{"x":-184,"y":32,"z":176},{"x":-152,"y":32,"z":172},{"x":-148,"y":36,"z":200},{"x":-180,"y":36,"z":208}]},{"type":"quad","texture":"texMetalHangar01","frame":0,"position":{"x":0,"y":0,"z":0},"points":[{"x":-152,"y":32,"z":172},{"x":-120,"y":32,"z":168},{"x":-116,"y":36,"z":192},{"x":-148,"y":36,"z":200}]},{"type":"quad","texture":"sprDebugTexture","frame":0,"position":{"x":0,"y":0,"z":0},"points":[{"x":-180,"y":36,"z":208},{"x":-148,"y":36,"z":200},{"x":-136,"y":40,"z":228},{"x":-168,"y":40,"z":240}]},{"type":"quad","texture":"texMetalHangar00","frame":0,"position":{"x":0,"y":0,"z":0},"points":[{"x":-148,"y":36,"z":200},{"x":-116,"y":36,"z":192},{"x":-108,"y":40,"z":212},{"x":-136,"y":40,"z":228}]},{"type":"quad","texture":"texMetalHangarLineCurve","frame":0,"position":{"x":0,"y":0,"z":0},"points":[{"x":-136,"y":40,"z":228},{"x":-108,"y":40,"z":212},{"x":-92,"y":44,"z":228},{"x":-116,"y":44,"z":252}]},{"type":"quad","texture":"texMetalHangarLineStraight","frame":0,"position":{"x":0,"y":0,"z":0},"points":[{"x":-180,"y":36,"z":208},{"x":-148,"y":36,"z":200},{"x":-136,"y":40,"z":228},{"x":-168,"y":40,"z":240}]},{"type":"quad","texture":"texMetalHangarLineCurve","frame":0,"position":{"x":0,"y":0,"z":0},"points":[{"x":-116,"y":44,"z":252},{"x":-140,"y":44,"z":272},{"x":-168,"y":40,"z":240},{"x":-136,"y":40,"z":228}]},{"type":"quad","texture":"texMetalHangarLineStraight","frame":0,"position":{"x":0,"y":0,"z":0},"points":[{"x":-116,"y":44,"z":252},{"x":-92,"y":44,"z":228},{"x":-72,"y":48,"z":236},{"x":-88,"y":48,"z":268}]},{"type":"quad","texture":"texMetalHangar02","frame":0,"position":{"x":0,"y":0,"z":0},"points":[{"x":-140,"y":44,"z":272},{"x":-116,"y":44,"z":252},{"x":-88,"y":48,"z":268},{"x":-100,"y":48,"z":296}]},{"type":"quad","texture":"texMetalHangar00","frame":0,"position":{"x":0,"y":0,"z":0},"points":[{"x":-100,"y":48,"z":296},{"x":-88,"y":48,"z":268},{"x":-60,"y":52,"z":272},{"x":-64,"y":52,"z":304}]},{"type":"quad","texture":"texMetalHangarLineStraight","frame":0,"position":{"x":0,"y":0,"z":0},"points":[{"x":-88,"y":48,"z":268},{"x":-72,"y":48,"z":236},{"x":-56,"y":52,"z":240},{"x":-60,"y":52,"z":272}]},{"type":"quad","texture":"texMetalHangar00","frame":0,"position":{"x":0,"y":0,"z":0},"points":[{"x":-32,"y":0,"z":208},{"x":0,"y":0,"z":208},{"x":0,"y":0,"z":240},{"x":-32,"y":0,"z":240}]},{"type":"quad","texture":"texMetalHangarLineStraight","frame":0,"position":{"x":0,"y":0,"z":0},"points":[{"x":0,"y":0,"z":208},{"x":32,"y":0,"z":208},{"x":32,"y":0,"z":240},{"x":0,"y":0,"z":240}]},{"type":"quad","texture":"texMetalHangarLineStraight","frame":0,"position":{"x":0,"y":0,"z":0},"points":[{"x":-60,"y":52,"z":272},{"x":-56,"y":52,"z":240},{"x":-32,"y":56,"z":240},{"x":-32,"y":56,"z":272}]},{"type":"quad","texture":"texWallGrind01","frame":0,"position":{"x":0,"y":0,"z":0},"points":[{"x":-32,"y":0,"z":240},{"x":0,"y":0,"z":240},{"x":0,"y":24,"z":240},{"x":-32,"y":24,"z":240}]},{"type":"quad","texture":"texWallGrind00","frame":0,"position":{"x":0,"y":0,"z":0},"points":[{"x":0,"y":24,"z":240},{"x":32,"y":24,"z":240},{"x":32,"y":56,"z":240},{"x":0,"y":56,"z":240}]},{"type":"quad","texture":"texMetalHangar01","frame":0,"position":{"x":0,"y":0,"z":0},"points":[{"x":-60,"y":52,"z":272},{"x":-32,"y":56,"z":272},{"x":-32,"y":56,"z":304},{"x":-64,"y":52,"z":304}]},{"type":"quad","texture":"texMetalHangarLineStraight","frame":0,"position":{"x":0,"y":0,"z":0},"points":[{"x":-32,"y":56,"z":272},{"x":-32,"y":56,"z":240},{"x":0,"y":56,"z":240},{"x":0,"y":56,"z":272}]},{"type":"quad","texture":"texMetalHangar01","frame":0,"position":{"x":0,"y":0,"z":0},"points":[{"x":-32,"y":56,"z":272},{"x":0,"y":56,"z":272},{"x":0,"y":56,"z":304},{"x":-32,"y":56,"z":304}]},{"type":"quad","texture":"texMetalHangar00","frame":0,"position":{"x":0,"y":0,"z":0},"points":[{"x":0,"y":56,"z":272},{"x":32,"y":56,"z":272},{"x":32,"y":56,"z":304},{"x":0,"y":56,"z":304}]},{"type":"quad","texture":"texMetalHangarLineEnd","frame":0,"position":{"x":0,"y":0,"z":0},"points":[{"x":0,"y":56,"z":272},{"x":0,"y":56,"z":240},{"x":32,"y":56,"z":240},{"x":32,"y":56,"z":272}]},{"type":"quad","texture":"texWallGrind01","frame":0,"position":{"x":0,"y":0,"z":0},"points":[{"x":0,"y":0,"z":240},{"x":32,"y":0,"z":240},{"x":32,"y":24,"z":240},{"x":0,"y":24,"z":240}]},{"type":"quad","texture":"texWallGrind00","frame":0,"position":{"x":0,"y":0,"z":0},"points":[{"x":-32,"y":24,"z":240},{"x":0,"y":24,"z":240},{"x":0,"y":56,"z":240},{"x":-32,"y":56,"z":240}]},{"type":"quad","texture":"texWallGrind00","frame":0,"position":{"x":0,"y":0,"z":0},"points":[{"x":-56,"y":20,"z":240},{"x":-32,"y":24,"z":240},{"x":-32,"y":56,"z":240},{"x":-56,"y":52,"z":240}]},{"type":"quad","texture":"texWallGrind00","frame":0,"position":{"x":0,"y":0,"z":0},"points":[{"x":-72,"y":16,"z":236},{"x":-56,"y":20,"z":240},{"x":-56,"y":52,"z":240},{"x":-72,"y":48,"z":236}]},{"type":"quad","texture":"texWallGrind00","frame":0,"position":{"x":0,"y":0,"z":0},"points":[{"x":-92,"y":12,"z":228},{"x":-72,"y":16,"z":236},{"x":-72,"y":48,"z":236},{"x":-92,"y":44,"z":228}]},{"type":"quad","texture":"texWallGrind00","frame":0,"position":{"x":0,"y":0,"z":0},"points":[{"x":-108,"y":8,"z":212},{"x":-92,"y":12,"z":228},{"x":-92,"y":44,"z":228},{"x":-108,"y":40,"z":212}]},{"type":"quad","texture":"texWallGrind00","frame":0,"position":{"x":0,"y":0,"z":0},"points":[{"x":-116,"y":4,"z":192},{"x":-108,"y":8,"z":212},{"x":-108,"y":40,"z":212},{"x":-116,"y":36,"z":192}]},{"type":"quad","texture":"texWallGrind00","frame":0,"position":{"x":0,"y":0,"z":0},"points":[{"x":-120,"y":0,"z":168},{"x":-116,"y":4,"z":192},{"x":-116,"y":36,"z":192},{"x":-120,"y":32,"z":168}]},{"type":"quad","texture":"texWallGrind00","frame":0,"position":{"x":0,"y":0,"z":0},"points":[{"x":-120,"y":-4,"z":144},{"x":-120,"y":0,"z":168},{"x":-120,"y":32,"z":168},{"x":-120,"y":28,"z":144}]},{"type":"quad","texture":"texWallGrind00","frame":0,"position":{"x":0,"y":0,"z":0},"points":[{"x":-120,"y":-8,"z":120},{"x":-120,"y":-4,"z":144},{"x":-120,"y":28,"z":144},{"x":-120,"y":24,"z":120}]},{"type":"quad","texture":"texWallGrind00","frame":0,"position":{"x":0,"y":0,"z":0},"points":[{"x":-116,"y":-12,"z":96},{"x":-120,"y":-8,"z":120},{"x":-120,"y":24,"z":120},{"x":-116,"y":20,"z":96}]},{"type":"quad","texture":"texWallGrind00","frame":0,"position":{"x":0,"y":0,"z":0},"points":[{"x":-108,"y":-16,"z":76},{"x":-116,"y":-12,"z":96},{"x":-116,"y":20,"z":96},{"x":-108,"y":16,"z":76}]},{"type":"quad","texture":"texWallGrind00","frame":0,"position":{"x":0,"y":0,"z":0},"points":[{"x":-96,"y":-20,"z":64},{"x":-108,"y":-16,"z":76},{"x":-108,"y":16,"z":76},{"x":-96,"y":12,"z":64}]},{"type":"quad","texture":"texWallGrind00","frame":0,"position":{"x":0,"y":0,"z":0},"points":[{"x":-76,"y":-24,"z":52},{"x":-96,"y":-20,"z":64},{"x":-96,"y":12,"z":64},{"x":-76,"y":8,"z":52}]},{"type":"quad","texture":"texWallGrind00","frame":0,"position":{"x":0,"y":0,"z":0},"points":[{"x":-56,"y":-28,"z":48},{"x":-76,"y":-24,"z":52},{"x":-76,"y":8,"z":52},{"x":-56,"y":4,"z":48}]},{"type":"quad","texture":"texWallGrind00","frame":0,"position":{"x":0,"y":0,"z":0},"points":[{"x":-32,"y":-32,"z":48},{"x":-56,"y":-28,"z":48},{"x":-56,"y":4,"z":48},{"x":-32,"y":0,"z":48}]},{"type":"quad","texture":"texWallGrind00","frame":0,"position":{"x":0,"y":0,"z":0},"points":[{"x":-64,"y":-28,"z":-16},{"x":-32,"y":-32,"z":-16},{"x":-32,"y":0,"z":-16},{"x":-64,"y":4,"z":-16}]},{"type":"quad","texture":"texWallGrind00","frame":0,"position":{"x":0,"y":0,"z":0},"points":[{"x":-100,"y":-24,"z":-4},{"x":-64,"y":-28,"z":-16},{"x":-64,"y":4,"z":-16},{"x":-100,"y":8,"z":-4}]},{"type":"quad","texture":"texWallGrind00","frame":0,"position":{"x":0,"y":0,"z":0},"points":[{"x":-132,"y":-20,"z":16},{"x":-100,"y":-24,"z":-4},{"x":-100,"y":8,"z":-4},{"x":-132,"y":12,"z":16}]},{"type":"quad","texture":"texWallGrind00","frame":0,"position":{"x":0,"y":0,"z":0},"points":[{"x":-160,"y":-16,"z":44},{"x":-132,"y":-20,"z":16},{"x":-132,"y":12,"z":16},{"x":-160,"y":16,"z":44}]},{"type":"quad","texture":"texMetalHangar00","frame":0,"position":{"x":0,"y":0,"z":0},"points":[{"x":-160,"y":16,"z":44},{"x":-132,"y":12,"z":16},{"x":-116,"y":12,"z":40},{"x":-132,"y":16,"z":60}]},{"type":"quad","texture":"texWallGrind00","frame":0,"position":{"x":0,"y":0,"z":0},"points":[{"x":-176,"y":-12,"z":80},{"x":-160,"y":-16,"z":44},{"x":-160,"y":16,"z":44},{"x":-176,"y":20,"z":80}]},{"type":"quad","texture":"texWallGrind00","frame":0,"position":{"x":0,"y":0,"z":0},"points":[{"x":-184,"y":-8,"z":112},{"x":-176,"y":-12,"z":80},{"x":-176,"y":20,"z":80},{"x":-184,"y":24,"z":112}]},{"type":"quad","texture":"texWallGrind00","frame":0,"position":{"x":0,"y":0,"z":0},"points":[{"x":-184,"y":-4,"z":144},{"x":-184,"y":-8,"z":112},{"x":-184,"y":24,"z":112},{"x":-184,"y":28,"z":144}]},{"type":"quad","texture":"texWallGrind00","frame":0,"position":{"x":0,"y":0,"z":0},"points":[{"x":-184,"y":0,"z":176},{"x":-184,"y":-4,"z":144},{"x":-184,"y":28,"z":144},{"x":-184,"y":32,"z":176}]},{"type":"quad","texture":"texWallGrind00","frame":0,"position":{"x":0,"y":0,"z":0},"points":[{"x":-180,"y":4,"z":208},{"x":-184,"y":0,"z":176},{"x":-184,"y":32,"z":176},{"x":-180,"y":36,"z":208}]},{"type":"quad","texture":"texWallGrind00","frame":0,"position":{"x":0,"y":0,"z":0},"points":[{"x":-168,"y":8,"z":240},{"x":-180,"y":4,"z":208},{"x":-180,"y":36,"z":208},{"x":-168,"y":40,"z":240}]},{"type":"quad","texture":"texWallGrind00","frame":0,"position":{"x":0,"y":0,"z":0},"points":[{"x":-140,"y":12,"z":272},{"x":-168,"y":8,"z":240},{"x":-168,"y":40,"z":240},{"x":-140,"y":44,"z":272}]},{"type":"quad","texture":"texWallGrind00","frame":0,"position":{"x":0,"y":0,"z":0},"points":[{"x":-100,"y":16,"z":296},{"x":-140,"y":12,"z":272},{"x":-140,"y":44,"z":272},{"x":-100,"y":48,"z":296}]},{"type":"quad","texture":"texWallGrind00","frame":0,"position":{"x":0,"y":0,"z":0},"points":[{"x":-64,"y":20,"z":304},{"x":-100,"y":16,"z":296},{"x":-100,"y":48,"z":296},{"x":-64,"y":52,"z":304}]},{"type":"quad","texture":"texWallGrind00","frame":0,"position":{"x":0,"y":0,"z":0},"points":[{"x":-32,"y":24,"z":304},{"x":-64,"y":20,"z":304},{"x":-64,"y":52,"z":304},{"x":-32,"y":56,"z":304}]},{"type":"quad","texture":"texWallGrind00","frame":0,"position":{"x":0,"y":0,"z":0},"points":[{"x":-32,"y":24,"z":304},{"x":0,"y":24,"z":304},{"x":0,"y":56,"z":304},{"x":-32,"y":56,"z":304}]},{"type":"quad","texture":"texWallGrind00","frame":0,"position":{"x":0,"y":0,"z":0},"points":[{"x":0,"y":24,"z":304},{"x":32,"y":24,"z":304},{"x":32,"y":56,"z":304},{"x":0,"y":56,"z":304}]},{"type":"quad","texture":"texWallGrind01","frame":0,"position":{"x":0,"y":0,"z":0},"points":[{"x":0,"y":0,"z":304},{"x":32,"y":0,"z":304},{"x":32,"y":24,"z":304},{"x":0,"y":24,"z":304}]},{"type":"quad","texture":"texWallGrind01","frame":0,"position":{"x":0,"y":0,"z":0},"points":[{"x":-32,"y":0,"z":304},{"x":0,"y":0,"z":304},{"x":0,"y":24,"z":304},{"x":-32,"y":24,"z":304}]},{"type":"quad","texture":"texMetalHangar00","frame":0,"position":{"x":0,"y":0,"z":0},"points":[{"x":-32,"y":0,"z":240},{"x":0,"y":0,"z":240},{"x":0,"y":0,"z":272},{"x":-32,"y":0,"z":272}]},{"type":"quad","texture":"texMetalHangar01","frame":0,"position":{"x":0,"y":0,"z":0},"points":[{"x":-32,"y":0,"z":272},{"x":0,"y":0,"z":272},{"x":0,"y":0,"z":304},{"x":-32,"y":0,"z":304}]},{"type":"quad","texture":"texMetalHangarLineEnd","frame":0,"position":{"x":0,"y":0,"z":0},"points":[{"x":0,"y":0,"z":240},{"x":32,"y":0,"z":240},{"x":32,"y":0,"z":272},{"x":0,"y":0,"z":272}]},{"type":"quad","texture":"texMetalHangar00","frame":0,"position":{"x":0,"y":0,"z":0},"points":[{"x":0,"y":0,"z":272},{"x":32,"y":0,"z":272},{"x":32,"y":0,"z":304},{"x":0,"y":0,"z":304}]},{"type":"quad","texture":"texWallGrind00","frame":0,"position":{"x":0,"y":0,"z":0},"points":[{"x":0,"y":-32,"z":304},{"x":32,"y":-32,"z":304},{"x":32,"y":0,"z":304},{"x":0,"y":0,"z":304}]},{"type":"quad","texture":"texWallGrind00","frame":0,"position":{"x":0,"y":0,"z":0},"points":[{"x":-32,"y":-32,"z":304},{"x":0,"y":-32,"z":304},{"x":0,"y":0,"z":304},{"x":-32,"y":0,"z":304}]},{"type":"quad","texture":"texMetalHangar01","frame":0,"position":{"x":0,"y":0,"z":0},"points":[{"x":-32,"y":-12,"z":272},{"x":-32,"y":-12,"z":304},{"x":-32,"y":0,"z":304},{"x":-32,"y":0,"z":272}]},{"type":"quad","texture":"texMetalHangar01","frame":0,"position":{"x":0,"y":0,"z":0},"points":[{"x":-32,"y":-12,"z":240},{"x":-32,"y":-12,"z":272},{"x":-32,"y":0,"z":272},{"x":-32,"y":0,"z":240}]},{"type":"quad","texture":"texWallGrind00","frame":0,"position":{"x":0,"y":0,"z":0},"points":[{"x":-32,"y":-32,"z":208},{"x":-32,"y":-32,"z":240},{"x":-32,"y":0,"z":240},{"x":-32,"y":0,"z":208}]},{"type":"quad","texture":"texWallGrind00","frame":0,"position":{"x":0,"y":0,"z":0},"points":[{"x":-32,"y":-40,"z":176},{"x":-32,"y":-40,"z":208},{"x":-32,"y":0,"z":208},{"x":-32,"y":0,"z":176}]},{"type":"quad","texture":"texWallGrind00","frame":0,"position":{"x":0,"y":0,"z":0},"points":[{"x":-32,"y":-40,"z":144},{"x":-32,"y":-40,"z":176},{"x":-32,"y":0,"z":176},{"x":-32,"y":0,"z":144}]},{"type":"quad","texture":"texWallGrind00","frame":0,"position":{"x":0,"y":0,"z":0},"points":[{"x":-32,"y":-40,"z":112},{"x":-32,"y":-40,"z":144},{"x":-32,"y":0,"z":144},{"x":-32,"y":0,"z":112}]},{"type":"quad","texture":"texWallGrind00","frame":0,"position":{"x":0,"y":0,"z":0},"points":[{"x":-32,"y":-40,"z":80},{"x":-32,"y":-40,"z":112},{"x":-32,"y":0,"z":112},{"x":-32,"y":0,"z":80}]},{"type":"quad","texture":"texWallGrind00","frame":0,"position":{"x":0,"y":0,"z":0},"points":[{"x":-32,"y":-40,"z":48},{"x":-32,"y":-40,"z":80},{"x":-32,"y":0,"z":80},{"x":-32,"y":0,"z":48}]},{"type":"quad","texture":"texWallGrind00","frame":0,"position":{"x":0,"y":0,"z":0},"points":[{"x":32,"y":-32,"z":-16},{"x":32,"y":-32,"z":16},{"x":32,"y":0,"z":16},{"x":32,"y":0,"z":-16}]},{"type":"quad","texture":"texWallGrind00","frame":0,"position":{"x":0,"y":0,"z":0},"points":[{"x":32,"y":-32,"z":16},{"x":32,"y":-32,"z":48},{"x":32,"y":0,"z":48},{"x":32,"y":0,"z":16}]},{"type":"quad","texture":"texWallGrind00","frame":0,"position":{"x":0,"y":0,"z":0},"points":[{"x":32,"y":-40,"z":48},{"x":32,"y":-40,"z":80},{"x":32,"y":0,"z":80},{"x":32,"y":0,"z":48}]},{"type":"quad","texture":"texWallGrind00","frame":0,"position":{"x":0,"y":0,"z":0},"points":[{"x":32,"y":-40,"z":80},{"x":32,"y":-40,"z":112},{"x":32,"y":0,"z":112},{"x":32,"y":0,"z":80}]},{"type":"quad","texture":"texWallGrind00","frame":0,"position":{"x":0,"y":0,"z":0},"points":[{"x":32,"y":-40,"z":112},{"x":32,"y":-40,"z":144},{"x":32,"y":0,"z":144},{"x":32,"y":0,"z":112}]},{"type":"quad","texture":"texWallGrind00","frame":0,"position":{"x":0,"y":0,"z":0},"points":[{"x":32,"y":-40,"z":144},{"x":32,"y":-40,"z":176},{"x":32,"y":0,"z":176},{"x":32,"y":0,"z":144}]},{"type":"quad","texture":"texWallGrind00","frame":0,"position":{"x":0,"y":0,"z":0},"points":[{"x":32,"y":-40,"z":176},{"x":32,"y":-40,"z":208},{"x":32,"y":0,"z":208},{"x":32,"y":0,"z":176}]},{"type":"quad","texture":"texMetalHangar01","frame":0,"position":{"x":0,"y":0,"z":0},"points":[{"x":52,"y":-32,"z":208},{"x":52,"y":-32,"z":224},{"x":48,"y":0,"z":224},{"x":48,"y":0,"z":208}]},{"type":"quad","texture":"texMetalHangar01","frame":0,"position":{"x":0,"y":0,"z":0},"points":[{"x":52,"y":-32,"z":288},{"x":52,"y":-32,"z":304},{"x":48,"y":0,"z":304},{"x":48,"y":0,"z":288}]},{"type":"quad","texture":"texMetalHangar01","frame":0,"position":{"x":0,"y":0,"z":0},"points":[{"x":32,"y":0,"z":272},{"x":48,"y":0,"z":272},{"x":48,"y":0,"z":304},{"x":32,"y":0,"z":304}]},{"type":"quad","texture":"texMetalHangar02","frame":0,"position":{"x":0,"y":0,"z":0},"points":[{"x":32,"y":0,"z":240},{"x":48,"y":0,"z":240},{"x":48,"y":0,"z":272},{"x":32,"y":0,"z":272}]},{"type":"quad","texture":"texMetalHangar00","frame":0,"position":{"x":0,"y":0,"z":0},"points":[{"x":32,"y":0,"z":208},{"x":48,"y":0,"z":208},{"x":48,"y":0,"z":240},{"x":32,"y":0,"z":240}]},{"type":"quad","texture":"texWallGrind00","frame":0,"position":{"x":0,"y":0,"z":0},"points":[{"x":32,"y":-32,"z":304},{"x":52,"y":-32,"z":304},{"x":48,"y":0,"z":304},{"x":32,"y":0,"z":304}]},{"type":"quad","texture":"texWallGrind00","frame":0,"position":{"x":0,"y":0,"z":0},"points":[{"x":32,"y":-32,"z":208},{"x":52,"y":-32,"z":208},{"x":48,"y":0,"z":208},{"x":32,"y":0,"z":208}]},{"type":"quad","texture":"texGlass00","frame":0,"position":{"x":0,"y":0,"z":0},"points":[{"x":-32,"y":-28,"z":244},{"x":-32,"y":-28,"z":272},{"x":-32,"y":-12,"z":272},{"x":-32,"y":-12,"z":244}]},{"type":"quad","texture":"texGlass00","frame":0,"position":{"x":0,"y":0,"z":0},"points":[{"x":-32,"y":-28,"z":272},{"x":-32,"y":-28,"z":300},{"x":-32,"y":-12,"z":300},{"x":-32,"y":-12,"z":272}]},{"type":"quad","texture":"texMetalHangar02","frame":0,"position":{"x":0,"y":0,"z":0},"points":[{"x":-32,"y":-28,"z":240},{"x":-32,"y":-28,"z":244},{"x":-32,"y":-12,"z":244},{"x":-32,"y":-12,"z":240}]},{"type":"quad","texture":"texMetalHangar01","frame":0,"position":{"x":0,"y":0,"z":0},"points":[{"x":-32,"y":-28,"z":300},{"x":-32,"y":-28,"z":304},{"x":-32,"y":-12,"z":304},{"x":-32,"y":-12,"z":300}]},{"type":"quad","texture":"texWallGrind01","frame":0,"position":{"x":0,"y":0,"z":0},"points":[{"x":-56,"y":0,"z":240},{"x":-32,"y":0,"z":240},{"x":-32,"y":24,"z":240},{"x":-56,"y":20,"z":240}]},{"type":"quad","texture":"texWallGrind00","frame":0,"position":{"x":0,"y":0,"z":0},"points":[{"x":16,"y":-32,"z":-16},{"x":32,"y":-32,"z":-16},{"x":32,"y":0,"z":-16},{"x":16,"y":0,"z":-16}]},{"type":"quad","texture":"texWallGrind00","frame":0,"position":{"x":0,"y":0,"z":0},"points":[{"x":-32,"y":-32,"z":-16},{"x":-16,"y":-32,"z":-16},{"x":-16,"y":0,"z":-16},{"x":-32,"y":0,"z":-16}]},{"type":"quad","texture":"texWallGrind01","frame":0,"position":{"x":0,"y":0,"z":0},"points":[{"x":0,"y":-40,"z":48},{"x":0,"y":-40,"z":80},{"x":-32,"y":-40,"z":80},{"x":-32,"y":-40,"z":48}]},{"type":"quad","texture":"texWallGrind01","frame":0,"position":{"x":0,"y":0,"z":0},"points":[{"x":0,"y":-40,"z":80},{"x":0,"y":-40,"z":112},{"x":-32,"y":-40,"z":112},{"x":-32,"y":-40,"z":80}]},{"type":"quad","texture":"texWallGrind01","frame":0,"position":{"x":0,"y":0,"z":0},"points":[{"x":0,"y":-40,"z":112},{"x":0,"y":-40,"z":144},{"x":-32,"y":-40,"z":144},{"x":-32,"y":-40,"z":112}]},{"type":"quad","texture":"texWallGrind01","frame":0,"position":{"x":0,"y":0,"z":0},"points":[{"x":0,"y":-40,"z":144},{"x":0,"y":-40,"z":176},{"x":-32,"y":-40,"z":176},{"x":-32,"y":-40,"z":144}]},{"type":"quad","texture":"texWallGrind01","frame":0,"position":{"x":0,"y":0,"z":0},"points":[{"x":0,"y":-40,"z":176},{"x":0,"y":-40,"z":208},{"x":-32,"y":-40,"z":208},{"x":-32,"y":-40,"z":176}]},{"type":"quad","texture":"texWallGrind01","frame":0,"position":{"x":0,"y":0,"z":0},"points":[{"x":0,"y":-40,"z":208},{"x":0,"y":-40,"z":176},{"x":32,"y":-40,"z":176},{"x":32,"y":-40,"z":208}]},{"type":"quad","texture":"texWallGrind01","frame":0,"position":{"x":0,"y":0,"z":0},"points":[{"x":0,"y":-40,"z":176},{"x":0,"y":-40,"z":144},{"x":32,"y":-40,"z":144},{"x":32,"y":-40,"z":176}]},{"type":"quad","texture":"texWallGrind01","frame":0,"position":{"x":0,"y":0,"z":0},"points":[{"x":0,"y":-40,"z":144},{"x":0,"y":-40,"z":112},{"x":32,"y":-40,"z":112},{"x":32,"y":-40,"z":144}]},{"type":"quad","texture":"texWallGrind01","frame":0,"position":{"x":0,"y":0,"z":0},"points":[{"x":0,"y":-40,"z":112},{"x":0,"y":-40,"z":80},{"x":32,"y":-40,"z":80},{"x":32,"y":-40,"z":112}]},{"type":"quad","texture":"texWallGrind01","frame":0,"position":{"x":0,"y":0,"z":0},"points":[{"x":0,"y":-40,"z":80},{"x":0,"y":-40,"z":48},{"x":32,"y":-40,"z":48},{"x":32,"y":-40,"z":80}]}],"collisionData":[{"type":"collisionQuad","position":{"x":8,"y":0,"z":-52},"points":[{"x":-40,"y":0,"z":36},{"x":24,"y":0,"z":36},{"x":24,"y":0,"z":260},{"x":-40,"y":0,"z":260}]},{"type":"collisionQuad","position":{"x":8,"y":0,"z":-52},"points":[{"x":-40,"y":0,"z":260},{"x":40,"y":0,"z":260},{"x":40,"y":0,"z":356},{"x":-40,"y":0,"z":356}]},{"type":"collisionQuad","position":{"x":8,"y":0,"z":-52},"points":[{"x":-108,"y":8,"z":48},{"x":-40,"y":0,"z":36},{"x":-40,"y":0,"z":100},{"x":-84,"y":8,"z":104}]},{"type":"collisionQuad","position":{"x":8,"y":0,"z":-52},"points":[{"x":-168,"y":16,"z":96},{"x":-108,"y":8,"z":48},{"x":-84,"y":8,"z":104},{"x":-116,"y":16,"z":128}]},{"type":"collisionQuad","position":{"x":8,"y":0,"z":-52},"points":[{"x":-192,"y":24,"z":164},{"x":-168,"y":16,"z":96},{"x":-116,"y":16,"z":128},{"x":-128,"y":24,"z":172}]},{"type":"collisionQuad","position":{"x":8,"y":0,"z":-52},"points":[{"x":-192,"y":32,"z":228},{"x":-192,"y":24,"z":164},{"x":-128,"y":24,"z":172},{"x":-128,"y":32,"z":220}]},{"type":"collisionQuad","position":{"x":8,"y":0,"z":-52},"points":[{"x":-176,"y":40,"z":292},{"x":-192,"y":32,"z":228},{"x":-128,"y":32,"z":220},{"x":-116,"y":40,"z":264}]},{"type":"collisionQuad","position":{"x":8,"y":0,"z":-52},"points":[{"x":-108,"y":48,"z":348},{"x":-176,"y":40,"z":292},{"x":-116,"y":40,"z":264},{"x":-80,"y":48,"z":288}]},{"type":"collisionQuad","position":{"x":8,"y":0,"z":-52},"points":[{"x":-40,"y":56,"z":356},{"x":-108,"y":48,"z":348},{"x":-80,"y":48,"z":288},{"x":-40,"y":56,"z":292}]},{"type":"collisionQuad","position":{"x":8,"y":0,"z":-52},"points":[{"x":24,"y":56,"z":356},{"x":-40,"y":56,"z":356},{"x":-40,"y":56,"z":292},{"x":24,"y":56,"z":292}]}]}